{
  "url": "https://academy.creatio.com/docs/8.x/creatio-apps/creatio-basics/communications/creatio-ai/creatio-ai-add-in-overview",
  "title": "Enhance communication workflow using Creatio.ai",
  "breadcrumbs": [
    {
      "text": "Platform",
      "href": "/docs/8.x/creatio-apps/category/platform"
    },
    {
      "text": "Communications",
      "href": "/docs/8.x/creatio-apps/category/communications"
    },
    {
      "text": "Creatio.ai",
      "href": "/docs/8.x/creatio-apps/category/creatioai"
    }
  ],
  "content_markdown": "Version: 8.3\nOn this page\nYou can use Creatio.ai directly in Microsoft Outlook or Teams using a dedicated add-in. This lets you automate repetitive tasks, retrieve CRM insights, and interact with AI-powered virtual agent assistants to streamline sales operations. Sales and customer-facing professionals can prepare for meetings, access opportunities, and review contact data directly in their collaboration environment.\nThe Outlook version of the add-in provides a concise summary view for quick preparation, while the Teams version supports full conversational capabilities during live sessions.\nExample\nA sales representative opens the Creatio.ai add-in in Outlook and sets up a meeting. Before the session, they use Creatio.ai both in Outlook and Teams to prepare for the meeting, review related accounts and opportunities, and identify contacts to which the meeting was forwarded. When the meeting starts, they open the add-in in Teams to capture notes and clarify data. After the meeting they can make a recap of the info\u2014all without leaving Teams or Outlook.\n## Access Creatio AI in Microsoft Outlook\u200b\n1. Open **Microsoft Outlook** and **go to your calendar**.\n2. Select a meeting and **open the detailed view**.\n3. Go to the **Apps** section \u2192 **Creatio.ai**. This opens the add-in as a compact side panel. You can open the add-in from the **email window** in a similar way as well.\n4. **Review the contextual summary** prepared by Creatio.ai. The add-in displays key meeting data: participants, related accounts, and opportunity insights.\n5. Click **Join with Creatio.ai** to **continue the same AI-assisted conversation** in Microsoft Teams during the live meeting.\n## Access Creatio.ai in Microsoft Teams\u200b\n1. Open **Microsoft Teams** and **go to** the **Calendar** tab.\n2. Select a scheduled meeting and **open its detailed view**.\n3. **Click the Creatio.ai tab** or select **Chat** \u2192 **Creatio.ai**. The add-in opens as a dedicated tab within the meeting view.\n4. Click **Prepare for the sales meeting** to **start a contextual session**. Creatio.ai retrieves relevant emails and CRM data related to the meeting participants. The system identifies the related **accounts** , **contacts** , and **opportunities** from Creatio.\n5. **Review the summarized meeting context** that includes the following:\n* customer details and related opportunities\n* key stakeholders and current deal stages\n* product interests and AI-generated recommendations\n6. Use the **chat panel** to **ask follow-up questions** or **generate a custom meeting agenda**.\n7. Open the **Creatio.ai** side panel during the meeting from the meeting window to **continue the conversation** , **take notes** , or **verify CRM data in real time**.\n8. Reopen the same chat thread after the meeting to **review the AI-generated summary** or **add post-meeting notes**.\nThe Creatio.ai conversation remains linked to the specific meeting event. When you switch to another meeting, a new conversation starts automatically, preserving the context of each event.\n## Use AI Skills in Creatio.ai add-in\u200b\nCreatio.ai add-in comes with a set of pre-configured AI Skills that let you get started with intelligent automation right away. View the comprehensive list of out-of-the-box AI Skills available in Creatio.ai chat panel in the task pane and explanations on how you can benefit from them in the table below.\nName| Description| Benefits and use cases| Emails in Outlook| Meetings in Outlook and Teams  \n---|---|---|---|---  \nIdentify contacts| Detect existing contacts based on email participants and show recent history. Suggest creating new contacts if none are found.| Streamlines contact acquisition and profile enrichment. Reduces manual input and improves CRM data quality.| +| +  \nSummarize email| Generate a summary of the full email thread.| Saves time and accelerates decision-making by providing quick insight into long email threads.| +| -  \nReply to email| Draft a context-aware email response using the thread and Creatio data.| Improves response time and consistency. Boosts customer loyalty and agent performance.| +| -  \nCheck open cases| Search for open cases related to the current email and highlight if any are overdue.| Helps reduce missed follow-ups and improve resolution time and CSAT.| +| +  \nNew meeting| Find a slot for the meeting with the needed people.| Automates meeting scheduling, improves coordination, and saves time.| +| +  \nPrepare for the sales meeting| Generate personalized recommendations to prepare for a client meeting at the Opportunity stage.| Enables sales executives to prepare quickly and efficiently.| -| +  \n**Creatio.ai** add-in capabilities are not limited to AI Skills accessible via buttons of the Creatio.ai chat panel. You can run any active AI Skill granted by access rights. No-code developers that have access to the \"Can manage configuration elements\" (CanManageSolution) system operation can customize AI Skills based on your business needs. Learn more: [Develop Creatio.ai Skill](https://academy.creatio.com/documents?id=2535), [AI Skill development recommendations](https://academy.creatio.com/documents?id=2536), [Development specifics for AI Skills in the Creatio.ai Outlook add-in](https://academy.creatio.com/documents?id=2600).\n* * *\n## See also\u200b\n[Creatio.ai](https://academy.creatio.com/docs/8.x/no-code-customization/category/creatio-ai)\n[Set up Creatio.ai add-in for Microsoft Outlook](https://academy.creatio.com/documents?id=2618)\n[Set up Creatio.ai add-in for Microsoft Teams](https://academy.creatio.com/documents?id=2619)\n[Development specifics for AI Skills in the Creatio.ai Outlook add-in](https://academy.creatio.com/documents?id=2600)\n[Creatio.ai (developer documentation)](https://academy.creatio.com/docs/8.x/dev/development-on-creatio-platform/category/creatio-ai)\n[How to use Creatio.ai Outlook add-in](https://www.youtube.com/watch?v=r-DAvBG9a1A)",
  "code_examples": [],
  "tables": [
    {
      "headers": [],
      "rows": [
        [
          "Name",
          "Description",
          "Benefits and use cases",
          "Emails in Outlook",
          "Meetings in Outlook and Teams"
        ],
        [
          "Identify contacts",
          "Detect existing contacts based on email participants and show recent history. Suggest creating new contacts if none are found.",
          "Streamlines contact acquisition and profile enrichment. Reduces manual input and improves CRM data quality.",
          "+",
          "+"
        ],
        [
          "Summarize email",
          "Generate a summary of the full email thread.",
          "Saves time and accelerates decision-making by providing quick insight into long email threads.",
          "+",
          "-"
        ],
        [
          "Reply to email",
          "Draft a context-aware email response using the thread and Creatio data.",
          "Improves response time and consistency. Boosts customer loyalty and agent performance.",
          "+",
          "-"
        ],
        [
          "Check open cases",
          "Search for open cases related to the current email and highlight if any are overdue.",
          "Helps reduce missed follow-ups and improve resolution time and CSAT.",
          "+",
          "+"
        ],
        [
          "New meeting",
          "Find a slot for the meeting with the needed people.",
          "Automates meeting scheduling, improves coordination, and saves time.",
          "+",
          "+"
        ],
        [
          "Prepare for the sales meeting",
          "Generate personalized recommendations to prepare for a client meeting at the Opportunity stage.",
          "Enables sales executives to prepare quickly and efficiently.",
          "-",
          "+"
        ]
      ],
      "caption": "",
      "html": "<table><tbody><tr><th><p>Name</p></th><th><p>Description</p></th><th><p>Benefits and use cases</p></th><th><p>Emails in Outlook</p></th><th><p>Meetings in Outlook and Teams</p></th></tr><tr><td><p>Identify contacts</p></td><td><p>Detect existing contacts based on email participants and show recent history. Suggest creating new contacts if none are found.</p></td><td><p>Streamlines contact acquisition and profile enrichment. Reduces manual input and improves CRM data quality.</p></td><td><p>+</p></td><td><p>+</p></td></tr><tr><td><p>Summarize email</p></td><td><p>Generate a summary of the full email thread.</p></td><td><p>Saves time and accelerates decision-making by providing quick insight into long email threads.</p></td><td><p>+</p></td><td><p>-</p></td></tr><tr><td><p>Reply to email</p></td><td><p>Draft a context-aware email response using the thread and Creatio data.</p></td><td><p>Improves response time and consistency. Boosts customer loyalty and agent performance.</p></td><td><p>+</p></td><td><p>-</p></td></tr><tr><td><p>Check open cases</p></td><td><p>Search for open cases related to the current email and highlight if any are overdue.</p></td><td><p>Helps reduce missed follow-ups and improve resolution time and CSAT.</p></td><td><p>+</p></td><td><p>+</p></td></tr><tr><td><p>New meeting</p></td><td><p>Find a slot for the meeting with the needed people.</p></td><td><p>Automates meeting scheduling, improves coordination, and saves time.</p></td><td><p>+</p></td><td><p>+</p></td></tr><tr><td><p>Prepare for the sales meeting</p></td><td><p>Generate personalized recommendations to prepare for a client meeting at the Opportunity stage.</p></td><td><p>Enables sales executives to prepare quickly and efficiently.</p></td><td><p>-</p></td><td><p>+</p></td></tr></tbody></table>"
    }
  ],
  "callouts": [
    {
      "type": "info",
      "title": "Info",
      "content": "ExampleA sales representative opens the Creatio.ai add-in in Outlook and sets up a meeting. Before the session, they use Creatio.ai both in Outlook and Teams to prepare for the meeting, review related accounts and opportunities, and identify contacts to which the meeting was forwarded. When the meeting starts, they open the add-in in Teams to capture notes and clarify data. After the meeting they can make a recap of the info\u2014all without leaving Teams or Outlook.",
      "html": "<div class=\"theme-admonition theme-admonition-info alert alert--info admonition_WoCw\"><div class=\"admonitionHeading_TMsN\">Example</div><div class=\"admonitionContent_vXIg\"><p>A sales representative opens the Creatio.ai add-in in Outlook and sets up a meeting. Before the session, they use Creatio.ai both in Outlook and Teams to prepare for the meeting, review related accounts and opportunities, and identify contacts to which the meeting was forwarded. When the meeting starts, they open the add-in in Teams to capture notes and clarify data. After the meeting they can make a recap of the info\u2014all without leaving Teams or Outlook.</p></div></div>"
    },
    {
      "type": "note",
      "title": "Note",
      "content": "Example",
      "html": "<div class=\"admonitionHeading_TMsN\">Example</div>"
    },
    {
      "type": "note",
      "title": "Note",
      "content": "A sales representative opens the Creatio.ai add-in in Outlook and sets up a meeting. Before the session, they use Creatio.ai both in Outlook and Teams to prepare for the meeting, review related accounts and opportunities, and identify contacts to which the meeting was forwarded. When the meeting starts, they open the add-in in Teams to capture notes and clarify data. After the meeting they can make a recap of the info\u2014all without leaving Teams or Outlook.",
      "html": "<div class=\"admonitionContent_vXIg\"><p>A sales representative opens the Creatio.ai add-in in Outlook and sets up a meeting. Before the session, they use Creatio.ai both in Outlook and Teams to prepare for the meeting, review related accounts and opportunities, and identify contacts to which the meeting was forwarded. When the meeting starts, they open the add-in in Teams to capture notes and clarify data. After the meeting they can make a recap of the info\u2014all without leaving Teams or Outlook.</p></div>"
    }
  ],
  "images": [],
  "videos": [
    {
      "type": "link",
      "src": "https://www.youtube.com/watch?v=r-DAvBG9a1A",
      "text": "How to use Creatio.ai Outlook add-in"
    }
  ],
  "downloadables": [],
  "headings": [
    {
      "level": 1,
      "text": "Enhance communication workflow using Creatio.ai",
      "anchor": ""
    },
    {
      "level": 2,
      "text": "Access Creatio AI in Microsoft Outlook\u200b",
      "anchor": "title-2617-1"
    },
    {
      "level": 2,
      "text": "Access Creatio.ai in Microsoft Teams\u200b",
      "anchor": "title-2617-2"
    },
    {
      "level": 2,
      "text": "Use AI Skills in Creatio.ai add-in\u200b",
      "anchor": "title-2617-3"
    },
    {
      "level": 2,
      "text": "See also\u200b",
      "anchor": "see-also"
    }
  ],
  "api_docs": {
    "endpoints": [],
    "parameters": [
      {
        "name": "Identify contacts",
        "type": "Detect existing contacts based on email participants and show recent history. Suggest creating new contacts if none are found.",
        "description": "Streamlines contact acquisition and profile enrichment. Reduces manual input and improves CRM data quality.",
        "required": false
      },
      {
        "name": "Summarize email",
        "type": "Generate a summary of the full email thread.",
        "description": "Saves time and accelerates decision-making by providing quick insight into long email threads.",
        "required": false
      },
      {
        "name": "Reply to email",
        "type": "Draft a context-aware email response using the thread and Creatio data.",
        "description": "Improves response time and consistency. Boosts customer loyalty and agent performance.",
        "required": false
      },
      {
        "name": "Check open cases",
        "type": "Search for open cases related to the current email and highlight if any are overdue.",
        "description": "Helps reduce missed follow-ups and improve resolution time and CSAT.",
        "required": false
      },
      {
        "name": "New meeting",
        "type": "Find a slot for the meeting with the needed people.",
        "description": "Automates meeting scheduling, improves coordination, and saves time.",
        "required": false
      },
      {
        "name": "Prepare for the sales meeting",
        "type": "Generate personalized recommendations to prepare for a client meeting at the Opportunity stage.",
        "description": "Enables sales executives to prepare quickly and efficiently.",
        "required": false
      }
    ],
    "responses": [],
    "examples": []
  },
  "sidebar_items": [
    {
      "href": "/docs/8.x/",
      "text": "Guides",
      "active": false
    },
    {
      "href": "/docs/8.x/creatio-apps/creatio-basics/communications/creatio-ai/creatio-ai-add-in-overview",
      "text": "Add-in overview",
      "active": false
    },
    {
      "href": "/docs/8.x/creatio-apps/8.2/overview/platform-overview",
      "text": "8.2",
      "active": false
    },
    {
      "href": "/docs/8.x/creatio-apps/8.1/overview/platform-overview",
      "text": "8.1",
      "active": false
    },
    {
      "href": "/docs/8.x/creatio-apps/8.0/platform-basics/user-interface/creatio-interface",
      "text": "8.0",
      "active": false
    },
    {
      "href": "/docs/8.x/creatio-apps/category/overview",
      "text": "Overview",
      "active": false
    },
    {
      "href": "/docs/8.x/creatio-apps/overview/platform-overview",
      "text": "Creatio Studio",
      "active": false
    },
    {
      "href": "/docs/8.x/creatio-apps/overview/sales-creatio-overview",
      "text": "Sales",
      "active": false
    },
    {
      "href": "/docs/8.x/creatio-apps/overview/marketing-creatio-overview",
      "text": "Marketing",
      "active": false
    },
    {
      "href": "/docs/8.x/creatio-apps/overview/service-creatio-overview",
      "text": "Service",
      "active": false
    },
    {
      "href": "/docs/8.x/creatio-apps/overview/financial-services-creatio-overview",
      "text": "Financial Services",
      "active": false
    },
    {
      "href": "/docs/8.x/creatio-apps/category/platform",
      "text": "Platform",
      "active": false
    },
    {
      "href": "/docs/8.x/creatio-apps/category/freedom-ui",
      "text": "Freedom UI",
      "active": false
    },
    {
      "href": "/docs/8.x/creatio-apps/creatio-basics/freedomUI/creatio-freedom-shell",
      "text": "Overview",
      "active": false
    },
    {
      "href": "/docs/8.x/creatio-apps/creatio-basics/freedomUI/creatio-ai",
      "text": "Creatio.ai",
      "active": false
    },
    {
      "href": "/docs/8.x/creatio-apps/creatio-basics/freedomUI/manage-a-freedom-ui-list",
      "text": "Record list",
      "active": false
    },
    {
      "href": "/docs/8.x/creatio-apps/creatio-basics/freedomUI/record-pages",
      "text": "Record pages",
      "active": false
    },
    {
      "href": "/docs/8.x/creatio-apps/creatio-basics/freedomUI/search-records",
      "text": "Search records",
      "active": false
    },
    {
      "href": "/docs/8.x/creatio-apps/creatio-basics/freedomUI/timeline",
      "text": "Timeline",
      "active": false
    },
    {
      "href": "/docs/8.x/creatio-apps/creatio-basics/freedomUI/keyboard-shortcuts",
      "text": "Hotkeys",
      "active": false
    },
    {
      "href": "/docs/8.x/creatio-apps/creatio-basics/freedomUI/attachments-and-notes",
      "text": "Attachments",
      "active": false
    },
    {
      "href": "/docs/8.x/creatio-apps/category/business-data",
      "text": "Business data",
      "active": false
    },
    {
      "href": "/docs/8.x/creatio-apps/creatio-basics/business-data/filters",
      "text": "Filters",
      "active": false
    },
    {
      "href": "/docs/8.x/creatio-apps/creatio-basics/business-data/folders",
      "text": "Folders",
      "active": false
    },
    {
      "href": "/docs/8.x/creatio-apps/creatio-basics/business-data/summaries",
      "text": "Summaries",
      "active": false
    },
    {
      "href": "/docs/8.x/creatio-apps/creatio-basics/business-data/tags",
      "text": "Tags",
      "active": false
    },
    {
      "href": "/docs/8.x/creatio-apps/category/data-import",
      "text": "Data import",
      "active": false
    },
    {
      "href": "/docs/8.x/creatio-apps/category/analytics",
      "text": "Analytics",
      "active": false
    },
    {
      "href": "/docs/8.x/creatio-apps/creatio-basics/business-data/exporting-list-data-to-excel",
      "text": "Excel export",
      "active": false
    },
    {
      "href": "/docs/8.x/creatio-apps/creatio-basics/business-data/find-and-merge-duplicates",
      "text": "Duplicates",
      "active": false
    },
    {
      "href": "/docs/8.x/creatio-apps/creatio-basics/business-data/share-records",
      "text": "Share records",
      "active": false
    },
    {
      "href": "/docs/8.x/creatio-apps/creatio-basics/business-data/delete-records",
      "text": "Delete records",
      "active": false
    },
    {
      "href": "/docs/8.x/creatio-apps/category/communications",
      "text": "Communications",
      "active": false
    },
    {
      "href": "/docs/8.x/creatio-apps/creatio-basics/communications/check-notifications-and-process-tasks",
      "text": "Notifications",
      "active": false
    },
    {
      "href": "/docs/8.x/creatio-apps/creatio-basics/communications/approvals",
      "text": "Approvals",
      "active": false
    },
    {
      "href": "/docs/8.x/creatio-apps/category/creatioai",
      "text": "PreviousCreatio.ai",
      "active": false
    },
    {
      "href": "/docs/8.x/creatio-apps/creatio-basics/communications/creatio-ai/set-up-creatio-ai-add-in-for-outlook",
      "text": "NextSetup for Outlook",
      "active": false
    },
    {
      "href": "/docs/8.x/creatio-apps/creatio-basics/communications/creatio-ai/set-up-creatio-ai-add-in-for-teams",
      "text": "Setup for Teams",
      "active": false
    },
    {
      "href": "/docs/8.x/creatio-apps/creatio-basics/communications/managing-calls",
      "text": "Calls",
      "active": false
    },
    {
      "href": "/docs/8.x/creatio-apps/creatio-basics/communications/time-zones",
      "text": "Time zones",
      "active": false
    },
    {
      "href": "/docs/8.x/creatio-apps/creatio-basics/communications/working-with-emails",
      "text": "Emails",
      "active": false
    },
    {
      "href": "/docs/8.x/creatio-apps/creatio-basics/communications/work-with-chats",
      "text": "Chats",
      "active": false
    },
    {
      "href": "/docs/8.x/creatio-apps/creatio-basics/communications/work-with-message-templates",
      "text": "Message templates",
      "active": false
    },
    {
      "href": "/docs/8.x/creatio-apps/category/running-business-processes",
      "text": "Running business processes",
      "active": false
    },
    {
      "href": "/docs/8.x/creatio-apps/creatio-basics/running-business-processes/run-business-process",
      "text": "Run a process",
      "active": false
    },
    {
      "href": "/docs/8.x/creatio-apps/creatio-basics/running-business-processes/execute-process-steps",
      "text": "Execute a process",
      "active": false
    },
    {
      "href": "/docs/8.x/creatio-apps/creatio-basics/running-business-processes/resume-business-process",
      "text": "Resume a process",
      "active": false
    },
    {
      "href": "/docs/8.x/creatio-apps/creatio-basics/use-two-factor-authentication",
      "text": "Use two-factor authentication",
      "active": false
    },
    {
      "href": "/docs/8.x/creatio-apps/category/products",
      "text": "Products",
      "active": false
    },
    {
      "href": "/docs/8.x/creatio-apps/category/common-features",
      "text": "Common features",
      "active": false
    },
    {
      "href": "/docs/8.x/creatio-apps/category/marketing-tools",
      "text": "Marketing tools",
      "active": false
    },
    {
      "href": "/docs/8.x/creatio-apps/category/sales-tools",
      "text": "Sales tools",
      "active": false
    },
    {
      "href": "/docs/8.x/creatio-apps/category/service-tools",
      "text": "Service tools",
      "active": false
    },
    {
      "href": "/docs/8.x/creatio-apps/category/finance-and-banking",
      "text": "Finance and banking",
      "active": false
    },
    {
      "href": "/docs/8.x/creatio-apps/category/industry-cases",
      "text": "Industry cases",
      "active": false
    },
    {
      "href": "https://academy.creatio.com/docs/8.x/no-code-customization/category/creatio-ai",
      "text": "Creatio.ai",
      "active": false
    },
    {
      "href": "https://academy.creatio.com/docs/8.x/dev/development-on-creatio-platform/category/creatio-ai",
      "text": "Creatio.ai (developer documentation)",
      "active": false
    }
  ],
  "related_links": [],
  "version": "8.x",
  "crawled_at": "2026-01-15T05:43:54.968063"
}